MANIFEST.in
README.md
nose.cfg
requirements.txt
setup.py
hipy/__init__.py
hipy/hipy
hipy/parser.py
hipy.egg-info/PKG-INFO
hipy.egg-info/SOURCES.txt
hipy.egg-info/dependency_links.txt
hipy.egg-info/requires.txt
hipy.egg-info/top_level.txt