Metadata-Version: 1.1
Name: hipy
Version: 0.11
Summary: Convert Ruby output of older Hiera versions to equivalent Python or JSON data structures
Home-page: https://github.com/marthjod/hipy
Author: marthjod
Author-email: marthjod@gmail.com
License: MIT
Platform: UNKNOWN
Classifier: Development Status :: 4 - Beta
Classifier: Intended Audience :: Developers
Classifier: License :: OSI Approved :: MIT License
Classifier: Programming Language :: Python :: 2
Classifier: Programming Language :: Python :: 2.7
Classifier: Programming Language :: Python :: 3
Classifier: Programming Language :: Python :: 3.4
Classifier: Programming Language :: Python :: 3.5
